lightconf/__init__.py
lightconf-22.2.0.dist-info/LICENSE
lightconf-22.2.0.dist-info/METADATA
lightconf-22.2.0.dist-info/WHEEL
lightconf-22.2.0.dist-info/top_level.txt
lightconf-22.2.0.dist-info/RECORD
